duck_client/__init__.py
duck_client/_db.py
duck_client/db.py
duck_client/error.py
duck_client-0.1.27.dist-info/METADATA
duck_client-0.1.27.dist-info/WHEEL
duck_client-0.1.27.dist-info/RECORD
