Metadata-Version: 2.3
Name: duck_client
Version: 0.1.27
Summary: 
Author: River.Shi
Author-email: nachuan.shi.quant@gamil.com
Requires-Python: >=3.10,<3.14
Classifier: Programming Language :: Python :: 3
Classifier: Programming Language :: Python :: 3.10
Classifier: Programming Language :: Python :: 3.11
Classifier: Programming Language :: Python :: 3.12
Classifier: Programming Language :: Python :: 3.13
Requires-Dist: duckdb (>=1.1.3,<2.0.0)
Requires-Dist: numpy (<=2.1)
Requires-Dist: pandas (>=2.2.3,<3.0.0)
Requires-Dist: pyarrow (>=21.0.0)
Requires-Dist: requests (>=2.32.4)
Requires-Dist: tqdm (>=4.67.1,<5.0.0)
